torah_dl/__init__.py
torah_dl/cli.py
torah_dl/py.typed
torah_dl/core/__init__.py
torah_dl/core/download.py
torah_dl/core/exceptions.py
torah_dl/core/extract.py
torah_dl/core/list.py
torah_dl/core/models.py
torah_dl/core/extractors/__init__.py
torah_dl/core/extractors/alldaf.py
torah_dl/core/extractors/naaleh.py
torah_dl/core/extractors/outorah.py
torah_dl/core/extractors/torahanytime.py
torah_dl/core/extractors/torahapp.py
torah_dl/core/extractors/torahdownloads.py
torah_dl/core/extractors/yutorah.py
torah_dl-0.5.0.dist-info/METADATA
torah_dl-0.5.0.dist-info/WHEEL
torah_dl-0.5.0.dist-info/entry_points.txt
torah_dl-0.5.0.dist-info/licenses/LICENSE
torah_dl-0.5.0.dist-info/RECORD
