Metadata-Version: 2.4
Name: torah-dl
Version: 0.5.0
Summary: SoferAI's Torah Downloader
Author-email: Matanya Loewenthal <matanya@loewenthal.net>
License-File: LICENSE
Classifier: Development Status :: 4 - Beta
Classifier: Environment :: Console
Classifier: Intended Audience :: Developers
Classifier: Intended Audience :: Religion
Classifier: License :: OSI Approved :: MIT License
Classifier: Operating System :: OS Independent
Classifier: Programming Language :: Python
Classifier: Programming Language :: Python :: 3
Classifier: Programming Language :: Python :: 3 :: Only
Classifier: Programming Language :: Python :: 3.10
Classifier: Programming Language :: Python :: 3.11
Classifier: Programming Language :: Python :: 3.12
Classifier: Programming Language :: Python :: 3.13
Classifier: Topic :: Software Development
Classifier: Topic :: Software Development :: Libraries
Classifier: Topic :: Software Development :: Libraries :: Python Modules
Classifier: Typing :: Typed
Requires-Python: >=3.10
Requires-Dist: bs4>=0.0.2
Requires-Dist: defusedxml>=0.6.0
Requires-Dist: pydantic>=2.11
Requires-Dist: requests>=2.0
Requires-Dist: urllib3>=2.0
Provides-Extra: cli
Requires-Dist: rich>=13.0.0; extra == 'cli'
Requires-Dist: typer>=0.14.0; extra == 'cli'
